pdfsak_version.py
pdfsak-1.3.4.data/scripts/pdfsak
pdfsak-1.3.4.data/scripts/pdfsak.bat
pdfsak-1.3.4.data/scripts/pdfsak_version.py
pdfsak-1.3.4.dist-info/LICENSE
pdfsak-1.3.4.dist-info/METADATA
pdfsak-1.3.4.dist-info/WHEEL
pdfsak-1.3.4.dist-info/top_level.txt
pdfsak-1.3.4.dist-info/RECORD
