Metadata-Version: 2.1
Name: pdfsak
Version: 1.3.4
Summary: Utility to manipulate PDF files
Home-page: https://github.com/raffaem/pdftools
Author: Raffaele Mancuso
Author-email: raffaelemancuso532@gmail.com
Project-URL: Bug Tracker, https://github.com/raffaem/pdftools/issues
Project-URL: Documentation, https://pdfsak.readthedocs.io
Classifier: Programming Language :: Python :: 3
Classifier: License :: OSI Approved :: MIT License
Classifier: Operating System :: OS Independent
Requires-Python: >=3.6
License-File: LICENSE
Requires-Dist: tqdm
Requires-Dist: natsort
Requires-Dist: packaging
